setup.cfg
setup.py
oauth2/__init__.py
oauth2/_version.py
oauth2/clients/__init__.py
oauth2/clients/imap.py
oauth2/clients/smtp.py
oauth2_utf8.egg-info/PKG-INFO
oauth2_utf8.egg-info/SOURCES.txt
oauth2_utf8.egg-info/dependency_links.txt
oauth2_utf8.egg-info/requires.txt
oauth2_utf8.egg-info/top_level.txt
oauth2_utf8.egg-info/zip-safe
tests/__init__.py
tests/test_oauth.py