Metadata-Version: 1.0
Name: oauth2-utf8
Version: 1.5.170
Summary: library for OAuth version 1.0 with to_url utf8 fix
Home-page: https://github.com/bxm156/python-oauth2
Author: Bryan Marty
Author-email: hello@bryanmarty.com
License: MIT License
Keywords: oauth
Platform: UNKNOWN
